README.md
setup.py
gymx/__init__.py
gymx/__main__.py
gymx/client.py
gymx/config.py
gymx/env_pb2.py
gymx/env_pb2_grpc.py
gymx/server.py
gymx.egg-info/PKG-INFO
gymx.egg-info/SOURCES.txt
gymx.egg-info/dependency_links.txt
gymx.egg-info/not-zip-safe
gymx.egg-info/requires.txt
gymx.egg-info/top_level.txt